{"class":"go.GraphLinksModel","linkFromPortIdProperty":"fromport","linkToPortIdProperty":"toport","modelData":{"position":"-172 -25"},"nodeDataArray":[{"category":"circle","text":"Start","key":"start","source":"../images/processFlow/start.png","figure":"circle","variables":[],"operatorConstant":"170","flowProperties":[{"inputParamData":[{"dataType":"com.mond.insurtech.crm.Account","fieldName":"customerInfo","isList":false}],"outputParamData":[{"dataType":"String","fieldName":"result","isList":false}]}],"comments":"Start","loc":"100 240"},{"category":"Stop","text":"End","figure":"circle","key":"end","source":"../images/processFlow/stop.png","operatorConstant":"171","comments":"End","loc":"950 240"}],"linkDataArray":[{"from":"start","to":"end","fromport":"R","toport":"L"}]}